web2llm/__init__.py
web2llm/cli.py
web2llm/config.py
web2llm/default_config.yaml
web2llm/errors.py
web2llm/output.py
web2llm/utils.py
web2llm/scrapers/__init__.py
web2llm/scrapers/base_scraper.py
web2llm/scrapers/generic_scraper.py
web2llm/scrapers/github_scraper.py
web2llm/scrapers/local_folder_scraper.py
web2llm/scrapers/pdf_scraper.py
web2llm-0.5.3.dist-info/licenses/LICENCE
web2llm-0.5.3.dist-info/METADATA
web2llm-0.5.3.dist-info/WHEEL
web2llm-0.5.3.dist-info/entry_points.txt
web2llm-0.5.3.dist-info/top_level.txt
web2llm-0.5.3.dist-info/RECORD
