Metadata-Version: 2.4
Name: web2llm
Version: 0.5.3
Summary: A tool to scrape web content into clean Markdown for LLMs.
Author-email: Juan Herruzo <juan@herruzo.dev>
License: MIT License
Project-URL: Homepage, https://github.com/herruzo99/web2llm
Project-URL: Bug Tracker, https://github.com/herruzo99/web2llm/issues
Keywords: scraper,llm,markdown,web scraping,pdf,github,rag
Classifier: Development Status :: 4 - Beta
Classifier: Programming Language :: Python :: 3
Classifier: Programming Language :: Python :: 3.10
Classifier: Programming Language :: Python :: 3.11
Classifier: Programming Language :: Python :: 3.12
Classifier: Programming Language :: Python :: 3.13
Classifier: License :: OSI Approved :: MIT License
Classifier: Operating System :: OS Independent
Classifier: Topic :: Text Processing
Classifier: Topic :: Utilities
Classifier: Environment :: Console
Requires-Python: >=3.10
License-File: LICENCE
Requires-Dist: beautifulsoup4
Requires-Dist: lxml
Requires-Dist: markdownify
Requires-Dist: GitPython
Requires-Dist: pdfplumber
Requires-Dist: PyYAML
Requires-Dist: pathspec
Requires-Dist: httpx[http2]
Provides-Extra: js
Requires-Dist: playwright; extra == "js"
Provides-Extra: test
Requires-Dist: pytest; extra == "test"
Requires-Dist: pytest-mock; extra == "test"
Requires-Dist: pytest-asyncio; extra == "test"
Provides-Extra: dev
Requires-Dist: ruff; extra == "dev"
Requires-Dist: pre-commit; extra == "dev"
Requires-Dist: web2llm[js,test]; extra == "dev"
Dynamic: license-file
